usgs/__init__.py
usgs/api.py
usgs/dataset.py
usgs/download.py
usgs/filters.py
usgs/manager.py
usgs/model.py
usgs/models.py
usgs/queries.py
usgs/query.py
usgs/relations.py
usgs/scene.py
usgs/tests/__init__.py
usgs/tests/conftest.py
usgs/tests/stubs/__init__.py
usgs/tests/stubs/dataset-search.json
usgs/tests/stubs/dataset.json
usgs/tests/stubs/download-options.json
usgs/tests/stubs/download-request.json
usgs/tests/stubs/download-retrieve.json
usgs/tests/stubs/login.json
usgs/tests/stubs/responses.py
usgs/tests/stubs/scene-search.json
usgs/tests/test_api_login.py
usgs/utilities.py
usgs_m2m_api-0.2.0.dist-info/WHEEL
usgs_m2m_api-0.2.0.dist-info/METADATA
usgs_m2m_api-0.2.0.dist-info/RECORD
