Metadata-Version: 2.1
Name: usgs-m2m-api
Version: 0.2.0
Summary: An object oriented method for working with the USGS EE machine-2-machine API v1.5
License: MIT
Author: Christopher Angel
Author-email: cangel@uark.edu
Requires-Python: >=3.9,<3.10
Classifier: License :: OSI Approved :: MIT License
Classifier: Programming Language :: Python :: 3
Classifier: Programming Language :: Python :: 3.9
Requires-Dist: clint (>=0.5.1,<0.6.0)
Requires-Dist: python-dateutil (>=2.8.2,<3.0.0)
Requires-Dist: python-dotenv (>=0.19.2,<0.20.0)
Requires-Dist: requests (>=2.26.0,<3.0.0)
Requires-Dist: urllib3 (==1.26.7)
